pybit/__init__.py
pybit/bits.py
pybit/multiplication.py
pybit/radix_convert.py
pybit_lib-0.1.0.dist-info/LICENSE
pybit_lib-0.1.0.dist-info/METADATA
pybit_lib-0.1.0.dist-info/WHEEL
pybit_lib-0.1.0.dist-info/top_level.txt
pybit_lib-0.1.0.dist-info/RECORD
